Metadata-Version: 2.1
Name: petdatasetreader
Version: 0.0.2
Summary: Convenient interface that provides structured representations of the PET dataset hosted on Huggingface
Home-page: https://pdi.fbk.eu/pet-dataset
Author: Patrizio Bellan
Author-email: patrizio.bellan@gmail.com
Maintainer: Patrizio Bellan
Maintainer-email: patrizio.bellan@gmail.com
License: MIT
Keywords: huggingface,PET,dataset,process extraction from text,natural language processing,nlp,business process management,bpm
Platform: Any
Classifier: License :: OSI Approved :: MIT License
Classifier: Natural Language :: English
Classifier: Intended Audience :: Science/Research
Classifier: Intended Audience :: Developers
Classifier: Intended Audience :: Education
Classifier: Intended Audience :: End Users/Desktop
Classifier: Intended Audience :: Information Technology
Classifier: Programming Language :: Python :: 3
Classifier: Programming Language :: Python :: 3.5
Classifier: Programming Language :: Python :: 3.6
Classifier: Programming Language :: Python :: 3.7
Classifier: Programming Language :: Python :: 3.8
Classifier: Programming Language :: Python :: 3.9
Classifier: Programming Language :: Python :: 3.10
Classifier: Programming Language :: Python :: 3.11
Classifier: Programming Language :: Python :: 3.12
Classifier: Topic :: Scientific/Engineering
Classifier: Topic :: Utilities
License-File: LICENSE.txt
Requires-Dist: datasets
